galemenu/__init__.py
GaleMenu-1.1.3.dist-info/LICENSE.txt
GaleMenu-1.1.3.dist-info/METADATA
GaleMenu-1.1.3.dist-info/WHEEL
GaleMenu-1.1.3.dist-info/top_level.txt
GaleMenu-1.1.3.dist-info/RECORD
