Metadata-Version: 2.1
Name: GaleMenu
Version: 1.1.3
Summary: Simple Python menu generator
Home-page: https://github.com/alex-gale/GaleMenu
Author: Alex Gale
License: MIT
Platform: UNKNOWN
